<?xml version="1.0"?>
<opencv_storage>
<stage7>
  <maxWeakCount>29</maxWeakCount>
  <stageThreshold>-1.0501267910003662e+00</stageThreshold>
  <weakClassifiers>
    <_>
      <internalNodes>
        0 -1 43621 -2.8721593320369720e-02</internalNodes>
      <leafValues>
        5.6036216020584106e-01 -3.0056178569793701e-01</leafValues></_>
    <_>
      <internalNodes>
        0 -1 43914 3.3461950719356537e-02</internalNodes>
      <leafValues>
        -1.9670484960079193e-01 5.6707793474197388e-01</leafValues></_>
    <_>
      <internalNodes>
        0 -1 24710 6.4364142715930939e-02</internalNodes>
      <leafValues>
        -1.9566383957862854e-01 4.7835031151771545e-01</leafValues></_>
    <_>
      <internalNodes>
        0 -1 43273 1.7560839653015137e-02</internalNodes>
      <leafValues>
        -1.7663317918777466e-01 5.3434675931930542e-01</leafValues></_>
    <_>
      <internalNodes>
        0 -1 72818 7.8505557030439377e-04</internalNodes>
      <leafValues>
        -1.7787083983421326e-01 3.6030408740043640e-01</leafValues></_>
    <_>
      <internalNodes>
        0 -1 49012 5.5680964142084122e-03</internalNodes>
      <leafValues>
        -2.0895799994468689e-01 3.4013605117797852e-01</leafValues></_>
    <_>
      <internalNodes>
        0 -1 48553 9.0647907927632332e-03</internalNodes>
      <leafValues>
        8.0576092004776001e-02 -8.0222171545028687e-01</leafValues></_>
    <_>
      <internalNodes>
        0 -1 49017 1.8589075654745102e-02</internalNodes>
      <leafValues>
        -1.2107987701892853e-01 5.7600200176239014e-01</leafValues></_>
    <_>
      <internalNodes>
        0 -1 68371 -1.5355909243226051e-02</internalNodes>
      <leafValues>
        3.9596614241600037e-01 -1.5392200648784637e-01</leafValues></_>
    <_>
      <internalNodes>
        0 -1 57829 -1.5061476267874241e-02</internalNodes>
      <leafValues>
        3.0800154805183411e-01 -2.1479032933712006e-01</leafValues></_>
    <_>
      <internalNodes>
        0 -1 54088 2.0237069576978683e-02</internalNodes>
      <leafValues>
        -1.0432270914316177e-01 5.7332283258438110e-01</leafValues></_>
    <_>
      <internalNodes>
        0 -1 70314 -3.3089546486735344e-03</internalNodes>
      <leafValues>
        1.3257606327533722e-01 -4.8887598514556885e-01</leafValues></_>
    <_>
      <internalNodes>
        0 -1 52648 -1.1822420638054609e-03</internalNodes>
      <leafValues>
        2.9227131605148315e-01 -2.0208558440208435e-01</leafValues></_>
    <_>
      <internalNodes>
        0 -1 43816 3.4230382880195975e-04</internalNodes>
      <leafValues>
        -2.6266384124755859e-01 2.0084768533706665e-01</leafValues></_>
    <_>
      <internalNodes>
        0 -1 65204 -3.4211813472211361e-03</internalNodes>
      <leafValues>
        -7.0183283090591431e-01 6.9595418870449066e-02</leafValues></_>
    <_>
      <internalNodes>
        0 -1 52689 2.3271194659173489e-03</internalNodes>
      <leafValues>
        -2.0781539380550385e-01 2.3160669207572937e-01</leafValues></_>
    <_>
      <internalNodes>
        0 -1 57065 7.6589910313487053e-03</internalNodes>
      <leafValues>
        6.4701162278652191e-02 -7.4180626869201660e-01</leafValues></_>
    <_>
      <internalNodes>
        0 -1 46941 -3.2978076487779617e-02</internalNodes>
      <leafValues>
        -9.5539098978042603e-01 3.8758639246225357e-02</leafValues></_>
    <_>
      <internalNodes>
        0 -1 58133 4.1770553216338158e-03</internalNodes>
      <leafValues>
        -1.5614013373851776e-01 3.2429161667823792e-01</leafValues></_>
    <_>
      <internalNodes>
        0 -1 38296 -5.1354728639125824e-02</internalNodes>
      <leafValues>
        -5.7196557521820068e-01 9.6659168601036072e-02</leafValues></_>
    <_>
      <internalNodes>
        0 -1 48761 -1.1466933414340019e-02</internalNodes>
      <leafValues>
        -7.9107630252838135e-01 5.2567832171916962e-02</leafValues></_>
    <_>
      <internalNodes>
        0 -1 48517 -7.4526690877974033e-04</internalNodes>
      <leafValues>
        1.6416029632091522e-01 -3.7021595239639282e-01</leafValues></_>
    <_>
      <internalNodes>
        0 -1 48885 -3.4303829073905945e-02</internalNodes>
      <leafValues>
        5.1304781436920166e-01 -1.0620564222335815e-01</leafValues></_>
    <_>
      <internalNodes>
        0 -1 48878 2.0599298179149628e-02</internalNodes>
      <leafValues>
        9.2951580882072449e-02 -5.8402305841445923e-01</leafValues></_>
    <_>
      <internalNodes>
        0 -1 53005 1.7760433256626129e-02</internalNodes>
      <leafValues>
        5.9509258717298508e-02 -7.8665715456008911e-01</leafValues></_>
    <_>
      <internalNodes>
        0 -1 77642 2.3940736427903175e-03</internalNodes>
      <leafValues>
        6.1660207808017731e-02 -6.4405393600463867e-01</leafValues></_>
    <_>
      <internalNodes>
        0 -1 58462 1.9911805167794228e-02</internalNodes>
      <leafValues>
        6.3669286668300629e-02 -6.5463310480117798e-01</leafValues></_>
    <_>
      <internalNodes>
        0 -1 44186 -1.6362493857741356e-02</internalNodes>
      <leafValues>
        3.1441622972488403e-01 -1.5899196267127991e-01</leafValues></_>
    <_>
      <internalNodes>
        0 -1 53292 -4.0738392621278763e-02</internalNodes>
      <leafValues>
        -9.0153497457504272e-01 6.1044622212648392e-02</leafValues></_></weakClassifiers></stage7>
</opencv_storage>
